pipeline/__init__.py
pipeline/ingest.py
pipeline/persist.py
pipeline/transform.py
datapipelinev1-1.0.1.dist-info/METADATA
datapipelinev1-1.0.1.dist-info/WHEEL
datapipelinev1-1.0.1.dist-info/top_level.txt
datapipelinev1-1.0.1.dist-info/RECORD
