Metadata-Version: 2.1
Name: datapipelinev1
Version: 1.0.1
Summary: will read csv file and remove rows with null values
Home-page: https://www.eaiesb.com
Author: Akhil
Author-email: akhil.kumar@eaiesb.com
License: UNKNOWN
Platform: UNKNOWN
Requires-Dist: pyspark
